auth/__init__.py
auth/base.py
auth/manager.py
commands/__init__.py
commands/auth.py
commands/client.py
commands/command.py
commands/filter.py
commands/manager.py
commands/player.py
commands/say.py
commands/server.py
commands/typed.py
config/__init__.py
config/command.py
config/cvar.py
config/manager.py
config/section.py
core/__init__.py
core/cache.py
core/dumps.py
core/logger.py
core/settings.py
core/table.py
core/update.py
core/version.py
core/command/__init__.py
core/command/auth.py
core/command/docs.py
core/command/dump.py
core/command/plugin.py
cvars/__init__.py
cvars/flags.py
cvars/public.py
cvars/tags.py
effects/__init__.py
effects/base.py
effects/hooks.py
effects/templates.py
engines/__init__.py
engines/gamerules.py
engines/precache.py
engines/server.py
engines/sound.py
engines/trace.py
entities/__init__.py
entities/_base.py
entities/classes.py
entities/constants.py
entities/datamaps.py
entities/dictionary.py
entities/entity.py
entities/factories.py
entities/helpers.py
entities/hooks.py
entities/props.py
entities/engines/__init__.py
entities/engines/csgo/__init__.py
entities/engines/csgo/csgo.py
events/__init__.py
events/custom.py
events/hooks.py
events/listener.py
events/manager.py
events/resource.py
events/variable.py
filters/__init__.py
filters/entities.py
filters/iterator.py
filters/players.py
filters/recipients.py
filters/weapons.py
hooks/__init__.py
hooks/base.py
hooks/exceptions.py
hooks/warnings.py
listeners/__init__.py
listeners/tick.py
memory/__init__.py
memory/helpers.py
memory/hooks.py
memory/manager.py
menus/__init__.py
menus/base.py
menus/esc.py
menus/queue.py
menus/radio.py
messages/__init__.py
messages/base.py
messages/dialog.py
messages/hooks.py
messages/impl.py
messages/colors/__init__.py
messages/colors/saytext2.py
players/__init__.py
players/_base.py
players/bots.py
players/constants.py
players/dictionary.py
players/entity.py
players/helpers.py
players/teams.py
players/voice.py
players/_language/__init__.py
players/_language/base.py
source_python-0.0.1.dist-info/LICENSE
source_python-0.0.1.dist-info/METADATA
source_python-0.0.1.dist-info/WHEEL
source_python-0.0.1.dist-info/top_level.txt
source_python-0.0.1.dist-info/RECORD
