Metadata-Version: 2.1
Name: source-python
Version: 0.0.1
Summary: Source.Python is an open-source project that uses boost::python to allow scripters to interact with Valve's Source-engine.
Home-page: https://github.com/Source-Python-Dev-Team/Source.Python
Author: Source-Python-Dev-Team
License: UNKNOWN
Platform: UNKNOWN
Requires-Python: >=3.6
